modelaudit/__init__.py
modelaudit/__main__.py
modelaudit/cli.py
modelaudit/core.py
modelaudit/models.py
modelaudit/telemetry.py
modelaudit/analysis/__init__.py
modelaudit/analysis/anomaly_detector.py
modelaudit/analysis/enhanced_pattern_detector.py
modelaudit/analysis/entropy_analyzer.py
modelaudit/analysis/framework_patterns.py
modelaudit/analysis/integrated_analyzer.py
modelaudit/analysis/ml_context_analyzer.py
modelaudit/analysis/opcode_sequence_analyzer.py
modelaudit/analysis/semantic_analyzer.py
modelaudit/analysis/unified_context.py
modelaudit/auth/__init__.py
modelaudit/auth/client.py
modelaudit/auth/config.py
modelaudit/cache/__init__.py
modelaudit/cache/batch_operations.py
modelaudit/cache/cache_manager.py
modelaudit/cache/optimized_config.py
modelaudit/cache/scan_results_cache.py
modelaudit/cache/smart_cache_keys.py
modelaudit/config/__init__.py
modelaudit/config/constants.py
modelaudit/config/explanations.py
modelaudit/config/name_blacklist.py
modelaudit/config/data/spdx_licenses.json
modelaudit/context/__init__.py
modelaudit/context/unified_context.py
modelaudit/detectors/__init__.py
modelaudit/detectors/cve_patterns.py
modelaudit/detectors/jit_script.py
modelaudit/detectors/network_comm.py
modelaudit/detectors/secrets.py
modelaudit/detectors/suspicious_symbols.py
modelaudit/integrations/__init__.py
modelaudit/integrations/jfrog.py
modelaudit/integrations/license_checker.py
modelaudit/integrations/mlflow.py
modelaudit/integrations/sarif_formatter.py
modelaudit/integrations/sbom_generator.py
modelaudit/knowledge/__init__.py
modelaudit/knowledge/framework_patterns.py
modelaudit/name_policies/__init__.py
modelaudit/name_policies/blacklist.py
modelaudit/progress/__init__.py
modelaudit/progress/base.py
modelaudit/progress/console.py
modelaudit/progress/file.py
modelaudit/progress/hooks.py
modelaudit/progress/multi_phase.py
modelaudit/scanners/__init__.py
modelaudit/scanners/base.py
modelaudit/scanners/executorch_scanner.py
modelaudit-0.2.23.dist-info/METADATA
modelaudit-0.2.23.dist-info/WHEEL
modelaudit-0.2.23.dist-info/entry_points.txt
modelaudit-0.2.23.dist-info/licenses/LICENSE
modelaudit-0.2.23.dist-info/RECORD
