Metadata-Version: 2.4
Name: modelaudit
Version: 0.2.23
Summary: Static scanning library for detecting malicious code, backdoors, and other security risks in ML model files
Project-URL: Repository, https://github.com/promptfoo/modelaudit
Project-URL: Homepage, https://github.com/promptfoo/modelaudit
Author-email: Ian Webster <ian@promptfoo.dev>, Michael D'Angelo <michael@promptfoo.dev>, Yash Chhabria <yash@promptfoo.dev>
License: MIT
License-File: LICENSE
Keywords: ai,ml,model-scanning,pickle,pytorch,security,tensorflow
Classifier: Development Status :: 4 - Beta
Classifier: Intended Audience :: Developers
Classifier: Programming Language :: Python :: 3
Classifier: Programming Language :: Python :: 3.10
Classifier: Programming Language :: Python :: 3.11
Classifier: Programming Language :: Python :: 3.12
Classifier: Programming Language :: Python :: 3.13
Classifier: Topic :: Scientific/Engineering :: Artificial Intelligence
Classifier: Topic :: Security
Requires-Python: >=3.10
Requires-Dist: click>=8.1.7
Requires-Dist: contourpy<1.3.3
Requires-Dist: cyclonedx-python-lib>=11.0.0
Requires-Dist: defusedxml>=0.7.1
Requires-Dist: fickling==0.1.4
Requires-Dist: fsspec>=2025.5.1
Requires-Dist: gcsfs>=2025.5.1
Requires-Dist: huggingface-hub>=0.23.0
Requires-Dist: numpy>=1.19.0
Requires-Dist: platformdirs>=3.0.0
Requires-Dist: posthog>=7.0.0
Requires-Dist: pydantic<3.0,>=2.11.0
Requires-Dist: python-dotenv>=1.0.0
Requires-Dist: pyyaml<7.0,>=6.0
Requires-Dist: requests>=2.28.0
Requires-Dist: s3fs>=2025.5.1
Requires-Dist: scipy>=1.7.0
Requires-Dist: yaspin>=2.5.0
Provides-Extra: all
Requires-Dist: dill<1.0,>=0.3.0; extra == 'all'
Requires-Dist: h5py<4.0,>=3.1; extra == 'all'
Requires-Dist: huggingface-hub>=0.23.0; extra == 'all'
Requires-Dist: joblib<2.0,>=1.0.0; extra == 'all'
Requires-Dist: mlflow>=2.12.0; extra == 'all'
Requires-Dist: msgpack<2.0,>=1.0.0; extra == 'all'
Requires-Dist: onnx<2.0,>=1.12.0; (python_version < '3.13') and extra == 'all'
Requires-Dist: py-ubjson>=0.16.0; extra == 'all'
Requires-Dist: pyyaml<7.0,>=6.0; extra == 'all'
Requires-Dist: safetensors>=0.4.0; extra == 'all'
Requires-Dist: scikit-learn<2.0,>=1.0.0; extra == 'all'
Requires-Dist: tensorflow<3.0,>=2.13.0; (python_version < '3.13') and extra == 'all'
Requires-Dist: tflite>=2.18.0; extra == 'all'
Requires-Dist: torch<3.0,>=2.6.0; extra == 'all'
Requires-Dist: xgboost<3.0,>=1.6.0; extra == 'all'
Provides-Extra: all-ci
Requires-Dist: dill<1.0,>=0.3.0; extra == 'all-ci'
Requires-Dist: h5py<4.0,>=3.1; extra == 'all-ci'
Requires-Dist: huggingface-hub>=0.23.0; extra == 'all-ci'
Requires-Dist: joblib<2.0,>=1.0.0; extra == 'all-ci'
Requires-Dist: mlflow>=2.12.0; extra == 'all-ci'
Requires-Dist: msgpack<2.0,>=1.0.0; extra == 'all-ci'
Requires-Dist: onnx<2.0,>=1.12.0; (python_version < '3.13') and extra == 'all-ci'
Requires-Dist: py-ubjson>=0.16.0; extra == 'all-ci'
Requires-Dist: pyyaml<7.0,>=6.0; extra == 'all-ci'
Requires-Dist: safetensors>=0.4.0; extra == 'all-ci'
Requires-Dist: scikit-learn<2.0,>=1.0.0; extra == 'all-ci'
Requires-Dist: tensorflow<3.0,>=2.13.0; (python_version < '3.13') and extra == 'all-ci'
Requires-Dist: tflite>=2.18.0; extra == 'all-ci'
Requires-Dist: torch<3.0,>=2.6.0; extra == 'all-ci'
Requires-Dist: xgboost<3.0,>=1.6.0; extra == 'all-ci'
Provides-Extra: dill
Requires-Dist: dill<1.0,>=0.3.0; extra == 'dill'
Provides-Extra: flax
Requires-Dist: msgpack<2.0,>=1.0.0; extra == 'flax'
Provides-Extra: h5
Requires-Dist: h5py<4.0,>=3.1; extra == 'h5'
Provides-Extra: huggingface
Requires-Dist: huggingface-hub>=0.23.0; extra == 'huggingface'
Provides-Extra: joblib
Requires-Dist: joblib<2.0,>=1.0.0; extra == 'joblib'
Requires-Dist: scikit-learn<2.0,>=1.0.0; extra == 'joblib'
Provides-Extra: mlflow
Requires-Dist: mlflow>=2.12.0; extra == 'mlflow'
Provides-Extra: numpy1
Requires-Dist: dill<1.0,>=0.3.0; extra == 'numpy1'
Requires-Dist: h5py<4.0,>=3.1; extra == 'numpy1'
Requires-Dist: huggingface-hub>=0.23.0; extra == 'numpy1'
Requires-Dist: joblib<2.0,>=1.0.0; extra == 'numpy1'
Requires-Dist: msgpack<2.0,>=1.0.0; extra == 'numpy1'
Requires-Dist: numpy<2.0,>=1.19.0; extra == 'numpy1'
Requires-Dist: onnx<2.0,>=1.12.0; (python_version < '3.13') and extra == 'numpy1'
Requires-Dist: pyyaml<7.0,>=6.0; extra == 'numpy1'
Requires-Dist: safetensors>=0.4.0; extra == 'numpy1'
Requires-Dist: scikit-learn<2.0,>=1.0.0; extra == 'numpy1'
Requires-Dist: tensorflow<3.0,>=2.13.0; (python_version < '3.13') and extra == 'numpy1'
Requires-Dist: tflite>=2.18.0; extra == 'numpy1'
Requires-Dist: torch<3.0,>=2.6.0; extra == 'numpy1'
Provides-Extra: onnx
Requires-Dist: onnx<2.0,>=1.12.0; (python_version < '3.13') and extra == 'onnx'
Provides-Extra: pytorch
Requires-Dist: torch<3.0,>=2.6.0; extra == 'pytorch'
Provides-Extra: safetensors
Requires-Dist: safetensors>=0.4.0; extra == 'safetensors'
Provides-Extra: sevenzip
Requires-Dist: py7zr>=0.20.0; extra == 'sevenzip'
Provides-Extra: tensorflow
Requires-Dist: tensorflow<3.0,>=2.13.0; (python_version < '3.13') and extra == 'tensorflow'
Provides-Extra: tensorrt
Requires-Dist: tensorrt>=8.6.0; (sys_platform == 'linux' or sys_platform == 'win32') and extra == 'tensorrt'
Provides-Extra: tflite
Requires-Dist: tflite>=2.18.0; extra == 'tflite'
Provides-Extra: xgboost
Requires-Dist: py-ubjson>=0.16.0; extra == 'xgboost'
Requires-Dist: xgboost<3.0,>=1.6.0; extra == 'xgboost'
Provides-Extra: yaml
Requires-Dist: pyyaml<7.0,>=6.0; extra == 'yaml'
